Metadata-Version: 2.1
Name: fixnames
Version: 0.2
Summary: Utility to scan and fix filenames with special characters by renaming them
Home-page: https://github.com/prahladyeri/fixnames
Author: Prahlad Yeri
Author-email: prahladyeri@yahoo.com
License: MIT
Keywords: utility,linux,windows
Platform: UNKNOWN
